{
    "CSS130930:014706-111135": {
        "name": "CSS130930:014706-111135",
        "aliases": [
            "CSS130930:014706-111135"
        ],
        "sources": [
            {
                "name": "ATEL 5437",
                "url": "http://www.astronomerstelegram.org/?read=5437",
                "alias": "1"
            },
            {
                "name": "Latest Supernovae",
                "url": "http://www.rochesterastronomy.org/snimages/snredshiftall.html",
                "alias": "2",
                "secondary": true
            },
            {
                "name": "Joseph Brimacombe",
                "alias": "3"
            }
        ],
        "discoverday": "29",
        "discoverer": "CRTS",
        "discovermonth": "9",
        "discoveryear": "2013",
        "maxappmag": "19",
        "maxday": "29",
        "maxmonth": "9",
        "maxyear": "2013",
        "sndec": "-11:11:34.8",
        "snra": "01:47:06.14",
        "photometry": [
            {
                "timeunit": "MJD",
                "time": "56564.5",
                "band": "",
                "abmag": "19.0",
                "source": "1,2"
            },
            {
                "timeunit": "MJD",
                "time": "56571.44",
                "band": "C",
                "abmag": "19.2",
                "source": "3,2"
            }
        ]
    }
}