{
	"PS1-14js":{
		"name":"PS1-14js",
		"aliases":[
			"PS1-14js"
		],
		"sources":[
			{
				"name":"PS1 SN page",
				"url":"http://star.pst.qub.ac.uk/ps1threepi/psdb/public/?page=1",
				"alias":"1"
			},
			{
				"name":"Latest Supernovae",
				"url":"http://www.rochesterastronomy.org/snimages/snredshiftall.html",
				"alias":"2",
				"secondary":true
			}
		],
		"discoverday":"23",
		"discoverer":"PS1",
		"discovermonth":"1",
		"discoveryear":"2014",
		"maxappmag":"19.7",
		"maxday":"23",
		"maxmonth":"1",
		"maxyear":"2014",
		"sndec":[
			{
				"value":"+07:04:16.4",
				"source":"1,2"
			}
		],
		"snra":[
			{
				"value":"10:26:16.52",
				"source":"1,2"
			}
		],
		"photometry":[
			{
				"timeunit":"MJD",
				"time":"56680.5",
				"band":"",
				"abmag":"19.7",
				"source":"1,2"
			}
		]
	}
}