{
	"PS1-13egu":{
		"name":"PS1-13egu",
		"aliases":[
			"PS1-13egu"
		],
		"sources":[
			{
				"name":"Pan-STARRS 3Pi",
				"url":"http://psweb.mp.qub.ac.uk/ps1threepi/psdb/",
				"alias":"1"
			}
		],
		"dec":[
			{
				"value":"-12:28:52.4",
				"source":"1",
				"unit":"degrees"
			}
		],
		"discoverdate":[
			{
				"value":"2013/11/29",
				"source":"D,1"
			}
		],
		"maxappmag":[
			{
				"value":"20.52",
				"source":"D,1"
			}
		],
		"maxband":[
			{
				"value":"g",
				"source":"D,1"
			}
		],
		"maxdate":[
			{
				"value":"2013/11/29",
				"source":"D,1"
			}
		],
		"ra":[
			{
				"value":"23:52:31.13",
				"source":"1",
				"unit":"hours"
			}
		],
		"photometry":[
			{
				"timeunit":"MJD",
				"time":"56467.6024499293",
				"band":"z",
				"magnitude":"20.4",
				"telescope":"Pan-STARRS1",
				"source":"1",
				"upperlimit":true
			},
			{
				"timeunit":"MJD",
				"time":"56474.602745437",
				"band":"y",
				"magnitude":"18.3",
				"telescope":"Pan-STARRS1",
				"source":"1",
				"upperlimit":true
			},
			{
				"timeunit":"MJD",
				"time":"56474.6266594273",
				"band":"y",
				"magnitude":"18.3",
				"telescope":"Pan-STARRS1",
				"source":"1",
				"upperlimit":true
			},
			{
				"timeunit":"MJD",
				"time":"56531.4855428297",
				"band":"r",
				"magnitude":"20.6",
				"telescope":"Pan-STARRS1",
				"source":"1",
				"upperlimit":true
			},
			{
				"timeunit":"MJD",
				"time":"56531.4965916317",
				"band":"r",
				"magnitude":"20.6",
				"telescope":"Pan-STARRS1",
				"source":"1",
				"upperlimit":true
			},
			{
				"timeunit":"MJD",
				"time":"56531.5090696751",
				"band":"i",
				"magnitude":"20.7",
				"telescope":"Pan-STARRS1",
				"source":"1",
				"upperlimit":true
			},
			{
				"timeunit":"MJD",
				"time":"56531.5211687666",
				"band":"i",
				"magnitude":"20.7",
				"telescope":"Pan-STARRS1",
				"source":"1",
				"upperlimit":true
			},
			{
				"timeunit":"MJD",
				"time":"56539.4408484884",
				"band":"g",
				"magnitude":"21.0",
				"telescope":"Pan-STARRS1",
				"source":"1",
				"upperlimit":true
			},
			{
				"timeunit":"MJD",
				"time":"56539.4524992546",
				"band":"g",
				"magnitude":"21.0",
				"telescope":"Pan-STARRS1",
				"source":"1",
				"upperlimit":true
			},
			{
				"timeunit":"MJD",
				"time":"56543.5181455272",
				"band":"g",
				"magnitude":"21.0",
				"telescope":"Pan-STARRS1",
				"source":"1",
				"upperlimit":true
			},
			{
				"timeunit":"MJD",
				"time":"56543.5304183066",
				"band":"g",
				"magnitude":"21.0",
				"telescope":"Pan-STARRS1",
				"source":"1",
				"upperlimit":true
			},
			{
				"timeunit":"MJD",
				"time":"56615.2079000529",
				"band":"y",
				"magnitude":"18.3",
				"telescope":"Pan-STARRS1",
				"source":"1",
				"upperlimit":true
			},
			{
				"timeunit":"MJD",
				"time":"56615.2287911157",
				"band":"z",
				"magnitude":"20.4",
				"telescope":"Pan-STARRS1",
				"source":"1",
				"upperlimit":true
			},
			{
				"timeunit":"MJD",
				"time":"56619.2317597186",
				"band":"r",
				"magnitude":"20.6",
				"telescope":"Pan-STARRS1",
				"source":"1",
				"upperlimit":true
			},
			{
				"timeunit":"MJD",
				"time":"56619.2431379295",
				"band":"r",
				"magnitude":"20.6",
				"telescope":"Pan-STARRS1",
				"source":"1",
				"upperlimit":true
			},
			{
				"timeunit":"MJD",
				"time":"56619.2563141007",
				"band":"i",
				"magnitude":"20.7",
				"telescope":"Pan-STARRS1",
				"source":"1",
				"upperlimit":true
			},
			{
				"timeunit":"MJD",
				"time":"56619.2690587411",
				"band":"i",
				"magnitude":"20.7",
				"telescope":"Pan-STARRS1",
				"source":"1",
				"upperlimit":true
			},
			{
				"timeunit":"MJD",
				"time":"56625.2377684725",
				"band":"g",
				"magnitude":"20.5298",
				"telescope":"Pan-STARRS1",
				"e_magnitude":"0.112238",
				"source":"1"
			},
			{
				"timeunit":"MJD",
				"time":"56625.2500593554",
				"band":"g",
				"magnitude":"20.5247",
				"telescope":"Pan-STARRS1",
				"e_magnitude":"0.0977985",
				"source":"1"
			},
			{
				"timeunit":"MJD",
				"time":"57004.1898029704",
				"band":"y",
				"magnitude":"18.3",
				"telescope":"Pan-STARRS1",
				"source":"1",
				"upperlimit":true
			},
			{
				"timeunit":"MJD",
				"time":"57005.1947867754",
				"band":"y",
				"magnitude":"18.3",
				"telescope":"Pan-STARRS1",
				"source":"1",
				"upperlimit":true
			},
			{
				"timeunit":"MJD",
				"time":"57244.6055737225",
				"band":"z",
				"magnitude":"20.4",
				"telescope":"Pan-STARRS1",
				"source":"1",
				"upperlimit":true
			},
			{
				"timeunit":"MJD",
				"time":"57244.6137712707",
				"band":"z",
				"magnitude":"20.4",
				"telescope":"Pan-STARRS1",
				"source":"1",
				"upperlimit":true
			},
			{
				"timeunit":"MJD",
				"time":"57353.2174821613",
				"band":"i",
				"magnitude":"20.7",
				"telescope":"Pan-STARRS1",
				"source":"1",
				"upperlimit":true
			},
			{
				"timeunit":"MJD",
				"time":"57353.228666069",
				"band":"i",
				"magnitude":"20.7",
				"telescope":"Pan-STARRS1",
				"source":"1",
				"upperlimit":true
			},
			{
				"timeunit":"MJD",
				"time":"57353.2398488339",
				"band":"i",
				"magnitude":"20.7",
				"telescope":"Pan-STARRS1",
				"source":"1",
				"upperlimit":true
			},
			{
				"timeunit":"MJD",
				"time":"57353.2510257588",
				"band":"i",
				"magnitude":"20.7",
				"telescope":"Pan-STARRS1",
				"source":"1",
				"upperlimit":true
			},
			{
				"timeunit":"MJD",
				"time":"57410.2082693456",
				"band":"y",
				"magnitude":"18.3",
				"telescope":"Pan-STARRS1",
				"source":"1",
				"upperlimit":true
			}
		]
	}
}