{
	"SN2013I":{
		"name":"SN2013I",
		"aliases":[
			"SN2013I",
			"DES12S1a"
		],
		"sources":[
			{
				"name":"Asiago Supernova Catalogue",
				"url":"http://graspa.oapd.inaf.it/cgi-bin/sncat.php",
				"alias":"1",
				"secondary":true
			},
			{
				"name":"CBET 3386",
				"url":"http://www.cbat.eps.harvard.edu/iau/cbet/003300/CBET003386.txt",
				"alias":"2"
			},
			{
				"name":"Latest Supernovae",
				"url":"http://www.rochesterastronomy.org/snimages/snredshiftall.html",
				"alias":"3",
				"secondary":true
			}
		],
		"claimedtype":[
			{
				"value":"Ia P",
				"source":"1"
			},
			{
				"value":"Ia",
				"source":"2,3"
			}
		],
		"discoverday":"4",
		"discoverer":[
			{
				"value":"Tanaka et al.",
				"source":"1"
			},
			{
				"value":"Dark Energy Survey",
				"source":"2,3"
			}
		],
		"discovermonth":"12",
		"discoveryear":"2012",
		"galdec":[
			{
				"value":"+00:45:35",
				"source":"1"
			}
		],
		"galra":[
			{
				"value":"02:49:43",
				"source":"1"
			}
		],
		"host":[
			{
				"value":"A024943+0045",
				"source":"1"
			}
		],
		"hvel":[
			{
				"value":"11000",
				"source":"D"
			}
		],
		"lumdist":[
			{
				"value":"160",
				"source":"D"
			}
		],
		"maxabsmag":"-18",
		"maxappmag":"17.8",
		"maxday":"10",
		"maxmonth":"1",
		"maxyear":"2012",
		"redshift":[
			{
				"value":"0.036",
				"source":"2,3"
			}
		],
		"sndec":[
			{
				"value":"+00:45:35.7",
				"source":"1,2,3"
			}
		],
		"snra":[
			{
				"value":"02:49:42.17",
				"source":"1,2,3"
			}
		],
		"photometry":[
			{
				"timeunit":"MJD",
				"time":"55936.5",
				"abmag":"17.8",
				"source":"2,3"
			}
		]
	}
}